{"230":{"id":"230","outgoingArcs":["244","245"],"incomingArcs":["55","111"],"position":[3.8097769,46.9878882]},"110":{"id":"110","outgoingArcs":["509","510"],"incomingArcs":["476","516"],"position":[3.8151915,46.9893023]},"231":{"id":"231","outgoingArcs":["111","112"],"incomingArcs":["122","245"],"position":[3.8096486,46.988101]},"111":{"id":"111","outgoingArcs":["475","476"],"incomingArcs":["455","510"],"position":[3.8154939,46.9890348]},"232":{"id":"232","outgoingArcs":["121","122","123"],"incomingArcs":["75","112","259"],"position":[3.8096134,46.9882692]},"112":{"id":"112","outgoingArcs":["455","456"],"incomingArcs":["437","475"],"position":[3.8156164,46.9889353]},"233":{"id":"233","outgoingArcs":["264","265","266"],"incomingArcs":["261","267","618"],"position":[3.8095905,46.9887298]},"113":{"id":"113","outgoingArcs":["436","437","438"],"incomingArcs":["419","444","456"],"position":[3.8159825,46.9887022]},"234":{"id":"234","outgoingArcs":["267","268"],"incomingArcs":["264","629"],"position":[3.8098086,46.9891468]},"114":{"id":"114","outgoingArcs":["35","36"],"incomingArcs":["30","550"],"position":[3.8134761,46.9918426]},"235":{"id":"235","outgoingArcs":["628","629","630"],"incomingArcs":["268","269","631"],"position":[3.8098302,46.9892068]},"115":{"id":"115","outgoingArcs":["550","551"],"incomingArcs":["36","549"],"position":[3.8136112,46.9916435]},"236":{"id":"236","outgoingArcs":["517","518"],"incomingArcs":["514","522"],"position":[3.8148293,46.9894409]},"116":{"id":"116","outgoingArcs":["548","549"],"incomingArcs":["546","551"],"position":[3.8136902,46.9915026]},"237":{"id":"237","outgoingArcs":["513","514"],"incomingArcs":["503","518"],"position":[3.8147801,46.9893485]},"117":{"id":"117","outgoingArcs":["546","547"],"incomingArcs":["545","548"],"position":[3.8138695,46.9911389]},"238":{"id":"238","outgoingArcs":["502","503"],"incomingArcs":["491","513"],"position":[3.8146433,46.9891543]},"118":{"id":"118","outgoingArcs":["544","545"],"incomingArcs":["543","547"],"position":[3.8139492,46.9910458]},"239":{"id":"239","outgoingArcs":["491","492"],"incomingArcs":["477","502"],"position":[3.8145722,46.9890916]},"119":{"id":"119","outgoingArcs":["542","543"],"incomingArcs":["541","544"],"position":[3.8140606,46.9909633]},"10":{"id":"10","outgoingArcs":["238","239"],"incomingArcs":["38","102"],"position":[3.811063,46.986257]},"11":{"id":"11","outgoingArcs":["101","102"],"incomingArcs":["238","591"],"position":[3.8107144,46.9865078]},"12":{"id":"12","outgoingArcs":["591","592","593"],"incomingArcs":["4","42","101"],"position":[3.8106377,46.986558]},"13":{"id":"13","outgoingArcs":["2","3","4"],"incomingArcs":["240","297","593"],"position":[3.8103179,46.9867673]},"14":{"id":"14","outgoingArcs":["240","241"],"incomingArcs":["3","139"],"position":[3.8098596,46.9870865]},"15":{"id":"15","outgoingArcs":["139","140"],"incomingArcs":["241","615"],"position":[3.809402,46.9875783]},"16":{"id":"16","outgoingArcs":["613","614","615"],"incomingArcs":["54","140","141"],"position":[3.8093912,46.9875919]},"17":{"id":"17","outgoingArcs":["141","142"],"incomingArcs":["248","614"],"position":[3.8091787,46.98786]},"18":{"id":"18","outgoingArcs":["246","247","248"],"incomingArcs":["142","250","252"],"position":[3.8090751,46.9879077]},"19":{"id":"19","outgoingArcs":["179","180","181"],"incomingArcs":["191","193","228"],"position":[3.8064732,46.9867109]},"240":{"id":"240","outgoingArcs":["477","478"],"incomingArcs":["464","492"],"position":[3.8145063,46.9890528]},"120":{"id":"120","outgoingArcs":["539","540","541"],"incomingArcs":["537","542","552"],"position":[3.8144333,46.9907077]},"241":{"id":"241","outgoingArcs":["463","464"],"incomingArcs":["450","478"],"position":[3.8144035,46.9890044]},"0":{"id":"0","outgoingArcs":["223","224","225"],"incomingArcs":["17","76","693"],"position":[3.8118395,46.9861768]},"121":{"id":"121","outgoingArcs":["452"],"incomingArcs":["473"],"closestDespawnNode":null,"position":[3.8040136,46.9888294]},"242":{"id":"242","outgoingArcs":["450","451"],"incomingArcs":["446","463"],"position":[3.8139545,46.9888233]},"1":{"id":"1","outgoingArcs":["17","18","19"],"incomingArcs":["66","225","670"],"position":[3.8116683,46.9861368]},"122":{"id":"122","outgoingArcs":["473","474"],"incomingArcs":["452","453"],"position":[3.8041833,46.9890287]},"243":{"id":"243","outgoingArcs":["446","447"],"incomingArcs":["440","451"],"position":[3.8138757,46.9887715]},"2":{"id":"2","outgoingArcs":["670","671"],"incomingArcs":["18","37"],"position":[3.8114111,46.9861241]},"123":{"id":"123","outgoingArcs":["453","454"],"incomingArcs":["441","474"],"position":[3.8044564,46.9889034]},"244":{"id":"244","outgoingArcs":["439","440"],"incomingArcs":["435","447"],"position":[3.8138319,46.9887217]},"3":{"id":"3","outgoingArcs":["37","38","39"],"incomingArcs":["239","553","671"],"position":[3.8111677,46.986138]},"124":{"id":"124","outgoingArcs":["441","442"],"incomingArcs":["428","454"],"position":[3.8047539,46.9887486]},"245":{"id":"245","outgoingArcs":["434","435"],"incomingArcs":["392","439"],"position":[3.813812,46.9886716]},"4":{"id":"4","outgoingArcs":["47","48"],"incomingArcs":["119","124"],"position":[3.8120353,46.9876896]},"125":{"id":"125","outgoingArcs":["411","412"],"incomingArcs":["380","427"],"position":[3.8056207,46.9883909]},"246":{"id":"246","outgoingArcs":["172"],"incomingArcs":["170"],"closestDespawnNode":null,"position":[3.8096255,46.9841575]},"5":{"id":"5","outgoingArcs":["119","120"],"incomingArcs":["47","117"],"position":[3.8116541,46.9875462]},"126":{"id":"126","outgoingArcs":["379","380","381"],"incomingArcs":["155","198","411"],"position":[3.8057153,46.9881012]},"247":{"id":"247","outgoingArcs":["170","171"],"incomingArcs":["172","188"],"position":[3.8096991,46.9842567]},"6":{"id":"6","outgoingArcs":["116","117","118"],"incomingArcs":["20","120","315"],"position":[3.8115866,46.9874884]},"127":{"id":"127","outgoingArcs":["552"],"incomingArcs":["540"],"closestDespawnNode":null,"position":[3.81444,46.9917175]},"248":{"id":"248","outgoingArcs":["618","619"],"incomingArcs":["266","616"],"position":[3.8098129,46.9887206]},"7":{"id":"7","outgoingArcs":["66","67"],"incomingArcs":["19","698"],"position":[3.8116456,46.9863411]},"128":{"id":"128","outgoingArcs":["537","538"],"incomingArcs":["535","539"],"position":[3.8144303,46.9902387]},"249":{"id":"249","outgoingArcs":["616","617"],"incomingArcs":["619","621"],"position":[3.809935,46.9887193]},"8":{"id":"8","outgoingArcs":["698","699"],"incomingArcs":["67","103"],"position":[3.811686,46.9866503]},"129":{"id":"129","outgoingArcs":["535","536"],"incomingArcs":["533","538"],"position":[3.8144447,46.9901394]},"9":{"id":"9","outgoingArcs":["103","104"],"incomingArcs":["134","699"],"position":[3.8116755,46.9868102]},"20":{"id":"20","outgoingArcs":["226","227","228"],"incomingArcs":["181","234","309"],"position":[3.8074666,46.986633]},"21":{"id":"21","outgoingArcs":["308","309","310"],"incomingArcs":["227","232","294"],"position":[3.8082676,46.9865456]},"22":{"id":"22","outgoingArcs":["293","294"],"incomingArcs":["209","308"],"position":[3.8089339,46.9864916]},"23":{"id":"23","outgoingArcs":["193"],"incomingArcs":["180"],"closestDespawnNode":null,"position":[3.8065052,46.9861518]},"24":{"id":"24","outgoingArcs":["191","192"],"incomingArcs":["179","186"],"position":[3.8063335,46.9872789]},"25":{"id":"25","outgoingArcs":["186","187"],"incomingArcs":["192","212"],"position":[3.8062774,46.9874824]},"26":{"id":"26","outgoingArcs":["211","212"],"incomingArcs":["187","362"],"position":[3.8062144,46.9875993]},"27":{"id":"27","outgoingArcs":["362","363"],"incomingArcs":["211","370"],"position":[3.8059672,46.9879001]},"28":{"id":"28","outgoingArcs":["370","371"],"incomingArcs":["157","363"],"position":[3.8059205,46.9879768]},"29":{"id":"29","outgoingArcs":["155","156","157"],"incomingArcs":["371","381","394"],"position":[3.8058499,46.9881809]},"250":{"id":"250","outgoingArcs":["620","621"],"incomingArcs":["617","623"],"position":[3.8100001,46.9887428]},"130":{"id":"130","outgoingArcs":["533","534"],"incomingArcs":["531","536"],"position":[3.8144769,46.9900574]},"251":{"id":"251","outgoingArcs":["622","623"],"incomingArcs":["620","624"],"position":[3.8100489,46.9888025]},"131":{"id":"131","outgoingArcs":["531","532"],"incomingArcs":["529","534"],"position":[3.8145297,46.9899676]},"252":{"id":"252","outgoingArcs":["624"],"incomingArcs":["622"],"closestDespawnNode":null,"position":[3.810238,46.9891119]},"132":{"id":"132","outgoingArcs":["529","530"],"incomingArcs":["527","532"],"position":[3.8147877,46.9896397]},"253":{"id":"253","outgoingArcs":["641"],"incomingArcs":["640"],"closestDespawnNode":null,"position":[3.8085356,46.9895414]},"133":{"id":"133","outgoingArcs":["527","528"],"incomingArcs":["521","530"],"position":[3.8148265,46.9895674]},"254":{"id":"254","outgoingArcs":["639","640"],"incomingArcs":["637","641"],"position":[3.8090888,46.9895012]},"134":{"id":"134","outgoingArcs":["257","258"],"incomingArcs":["256","262"],"position":[3.809237,46.9885814]},"255":{"id":"255","outgoingArcs":["637","638"],"incomingArcs":["635","639"],"position":[3.8092292,46.9894027]},"135":{"id":"135","outgoingArcs":["262","263"],"incomingArcs":["257","260"],"position":[3.8093894,46.9886074]},"256":{"id":"256","outgoingArcs":["635","636"],"incomingArcs":["632","638"],"position":[3.8093552,46.9893305]},"136":{"id":"136","outgoingArcs":["259","260","261"],"incomingArcs":["121","263","265"],"position":[3.8096054,46.9886052]},"257":{"id":"257","outgoingArcs":["631","632"],"incomingArcs":["628","636"],"position":[3.8095241,46.9892695]},"137":{"id":"137","outgoingArcs":["553","554"],"incomingArcs":["39","237"],"position":[3.8110145,46.986048]},"258":{"id":"258","outgoingArcs":["660","661"],"incomingArcs":["96","324"],"position":[3.8157037,46.9872403]},"138":{"id":"138","outgoingArcs":["168","169"],"incomingArcs":["189","655"],"position":[3.8098871,46.9847996]},"259":{"id":"259","outgoingArcs":["324","325"],"incomingArcs":["329","660"],"position":[3.8156813,46.987282]},"139":{"id":"139","outgoingArcs":["654","655"],"incomingArcs":["164","169"],"position":[3.8100204,46.9851083]},"30":{"id":"30","outgoingArcs":["206"],"incomingArcs":["185"],"closestDespawnNode":null,"position":[3.8055941,46.9860107]},"31":{"id":"31","outgoingArcs":["184","185"],"incomingArcs":["182","206"],"position":[3.8054732,46.9864349]},"32":{"id":"32","outgoingArcs":["182","183"],"incomingArcs":["178","184"],"position":[3.8054037,46.9866763]},"33":{"id":"33","outgoingArcs":["177","178"],"incomingArcs":["183","195"],"position":[3.8053478,46.9868404]},"34":{"id":"34","outgoingArcs":["194","195"],"incomingArcs":["175","177"],"position":[3.8052723,46.9870237]},"35":{"id":"35","outgoingArcs":["175","176"],"incomingArcs":["194","202"],"position":[3.8051212,46.9873009]},"36":{"id":"36","outgoingArcs":["202","203"],"incomingArcs":["176","199"],"position":[3.8049924,46.9874765]},"37":{"id":"37","outgoingArcs":["198","199"],"incomingArcs":["203","379"],"position":[3.8048872,46.987611]},"38":{"id":"38","outgoingArcs":["556","557"],"incomingArcs":["204","559"],"position":[3.8092219,46.9859429]},"39":{"id":"39","outgoingArcs":["204","205"],"incomingArcs":["200","556"],"position":[3.8091704,46.9858378]},"260":{"id":"260","outgoingArcs":["328","329"],"incomingArcs":["325","336"],"position":[3.815596,46.9873328]},"140":{"id":"140","outgoingArcs":["164","165"],"incomingArcs":["167","654"],"position":[3.8100706,46.9851965]},"261":{"id":"261","outgoingArcs":["336","337"],"incomingArcs":["328","340"],"position":[3.8152635,46.987478]},"141":{"id":"141","outgoingArcs":["166","167"],"incomingArcs":["165","236"],"position":[3.8105744,46.9857208]},"262":{"id":"262","outgoingArcs":["340","341"],"incomingArcs":["337","349"],"position":[3.8151083,46.9875435]},"142":{"id":"142","outgoingArcs":["236","237"],"incomingArcs":["166","554"],"position":[3.8109235,46.9859891]},"263":{"id":"263","outgoingArcs":["348","349"],"incomingArcs":["341","353"],"position":[3.8145941,46.9876845]},"143":{"id":"143","outgoingArcs":["559","560"],"incomingArcs":["173","557"],"position":[3.8093111,46.9861273]},"264":{"id":"264","outgoingArcs":["352","353"],"incomingArcs":["348","355"],"position":[3.8144705,46.9877279]},"144":{"id":"144","outgoingArcs":["577","578","579"],"incomingArcs":["569","575","581"],"position":[3.8093207,46.9863714]},"265":{"id":"265","outgoingArcs":["354","355"],"incomingArcs":["352","368"],"position":[3.8143739,46.9877712]},"145":{"id":"145","outgoingArcs":["569","570"],"incomingArcs":["174","579"],"position":[3.8093657,46.9862392]},"266":{"id":"266","outgoingArcs":["368","369"],"incomingArcs":["354","375"],"position":[3.814104,46.9879443]},"146":{"id":"146","outgoingArcs":["173","174"],"incomingArcs":["560","570"],"position":[3.8093509,46.9861973]},"267":{"id":"267","outgoingArcs":["374","375"],"incomingArcs":["369","386"],"position":[3.8140174,46.9880114]},"147":{"id":"147","outgoingArcs":["113"],"incomingArcs":["43"],"closestDespawnNode":null,"position":[3.8201951,46.9858978]},"268":{"id":"268","outgoingArcs":["384","385","386"],"incomingArcs":["374","387","391"],"position":[3.8138603,46.988147]},"148":{"id":"148","outgoingArcs":["43","44"],"incomingArcs":["113","300"],"position":[3.8197413,46.9859986]},"269":{"id":"269","outgoingArcs":["642","643"],"incomingArcs":["270","649"],"position":[3.8098638,46.9896566]},"149":{"id":"149","outgoingArcs":["76","77"],"incomingArcs":["223","673"],"position":[3.8120557,46.9862687]},"40":{"id":"40","outgoingArcs":["200","201"],"incomingArcs":["196","205"],"position":[3.8091538,46.9857202]},"41":{"id":"41","outgoingArcs":["196","197"],"incomingArcs":["201","658"],"position":[3.8092461,46.9850614]},"42":{"id":"42","outgoingArcs":["658","659"],"incomingArcs":["197","657"],"position":[3.8092943,46.9849379]},"43":{"id":"43","outgoingArcs":["656","657"],"incomingArcs":["207","659"],"position":[3.8093563,46.9848383]},"44":{"id":"44","outgoingArcs":["207","208"],"incomingArcs":["190","656"],"position":[3.8094603,46.9847649]},"45":{"id":"45","outgoingArcs":["188","189","190"],"incomingArcs":["168","171","208"],"position":[3.8098232,46.9846501]},"46":{"id":"46","outgoingArcs":["234","235"],"incomingArcs":["226","231"],"position":[3.8074824,46.987434]},"47":{"id":"47","outgoingArcs":["229","230","231"],"incomingArcs":["233","235","345"],"position":[3.8080457,46.9873644]},"48":{"id":"48","outgoingArcs":["232","233"],"incomingArcs":["230","310"],"position":[3.808285,46.9872471]},"49":{"id":"49","outgoingArcs":["40","41","42"],"incomingArcs":["69","316","592"],"position":[3.8112905,46.987085]},"270":{"id":"270","outgoingArcs":["649","650"],"incomingArcs":["642","652"],"position":[3.8098324,46.9899138]},"150":{"id":"150","outgoingArcs":["573","574"],"incomingArcs":["571","576"],"position":[3.8090095,46.9863219]},"271":{"id":"271","outgoingArcs":["651","652"],"incomingArcs":["650","653"],"position":[3.8096368,46.990418]},"151":{"id":"151","outgoingArcs":["575","576"],"incomingArcs":["573","577"],"position":[3.8091681,46.9863506]},"272":{"id":"272","outgoingArcs":["653"],"incomingArcs":["651"],"closestDespawnNode":null,"position":[3.8094786,46.9907927]},"152":{"id":"152","outgoingArcs":["558"],"incomingArcs":["572"],"closestDespawnNode":null,"position":[3.8082834,46.9860416]},"273":{"id":"273","outgoingArcs":["387","388"],"incomingArcs":["384","390"],"position":[3.8144563,46.9882075]},"153":{"id":"153","outgoingArcs":["571","572"],"incomingArcs":["558","574"],"position":[3.8088203,46.9862817]},"274":{"id":"274","outgoingArcs":["389","390"],"incomingArcs":["388","397"],"position":[3.8147023,46.9882335]},"154":{"id":"154","outgoingArcs":["20","21"],"incomingArcs":["93","116"],"position":[3.8114018,46.9875388]},"275":{"id":"275","outgoingArcs":["397","398"],"incomingArcs":["389","405"],"position":[3.8149057,46.9882675]},"155":{"id":"155","outgoingArcs":["92","93"],"incomingArcs":["21","29"],"position":[3.8112769,46.9875555]},"276":{"id":"276","outgoingArcs":["405","406"],"incomingArcs":["398","420"],"position":[3.815114,46.9883293]},"156":{"id":"156","outgoingArcs":["28","29"],"incomingArcs":["34","92"],"position":[3.8111686,46.9875513]},"277":{"id":"277","outgoingArcs":["419","420"],"incomingArcs":["406","438"],"position":[3.8154359,46.9884519]},"157":{"id":"157","outgoingArcs":["32","33","34"],"incomingArcs":["28","71","610"],"position":[3.8109866,46.9875566]},"278":{"id":"278","outgoingArcs":["13","14","15","16"],"incomingArcs":["129","360","382","696"],"position":[3.812498,46.9878287]},"158":{"id":"158","outgoingArcs":["132","133","134"],"incomingArcs":["82","104","317"],"position":[3.8115778,46.9870462]},"279":{"id":"279","outgoingArcs":["128","129","130","131"],"incomingArcs":["15","46","80","242"],"position":[3.8124804,46.9871105]},"159":{"id":"159","outgoingArcs":["82","83"],"incomingArcs":["133","681"],"position":[3.8116768,46.9870514]},"50":{"id":"50","outgoingArcs":["68","69"],"incomingArcs":["40","135"],"position":[3.8110382,46.9871543]},"51":{"id":"51","outgoingArcs":["135","136"],"incomingArcs":["68","612"],"position":[3.8109021,46.9871849]},"52":{"id":"52","outgoingArcs":["610","611","612"],"incomingArcs":["33","49","136"],"position":[3.8108758,46.987194]},"53":{"id":"53","outgoingArcs":["49","50"],"incomingArcs":["60","611"],"position":[3.8107789,46.9872276]},"54":{"id":"54","outgoingArcs":["60","61"],"incomingArcs":["50","127"],"position":[3.8106665,46.9872916]},"55":{"id":"55","outgoingArcs":["126","127"],"incomingArcs":["56","61"],"position":[3.8105523,46.9873598]},"56":{"id":"56","outgoingArcs":["56","57"],"incomingArcs":["106","126"],"position":[3.8103613,46.9874803]},"57":{"id":"57","outgoingArcs":["105","106"],"incomingArcs":["53","57"],"position":[3.810183,46.9875778]},"58":{"id":"58","outgoingArcs":["53","54","55"],"incomingArcs":["105","244","613"],"position":[3.8099147,46.9877269]},"59":{"id":"59","outgoingArcs":["251","252"],"incomingArcs":["247","253"],"position":[3.8090878,46.9880377]},"280":{"id":"280","outgoingArcs":["80","81"],"incomingArcs":["128","674"],"position":[3.8124308,46.9868578]},"160":{"id":"160","outgoingArcs":["145","146","147"],"incomingArcs":["162","376","418"],"position":[3.8076829,46.9883057]},"281":{"id":"281","outgoingArcs":["674","675"],"incomingArcs":["26","81"],"position":[3.8124132,46.9867745]},"161":{"id":"161","outgoingArcs":["417","418"],"incomingArcs":["146","432"],"position":[3.8075978,46.9884217]},"282":{"id":"282","outgoingArcs":["26","27"],"incomingArcs":["672","675"],"position":[3.8122715,46.986469]},"162":{"id":"162","outgoingArcs":["432","433"],"incomingArcs":["417","448"],"position":[3.8074527,46.9886618]},"283":{"id":"283","outgoingArcs":["672","673"],"incomingArcs":["27","77"],"position":[3.8121705,46.986361]},"163":{"id":"163","outgoingArcs":["607","608","609"],"incomingArcs":["9","605","691"],"position":[3.8128255,46.9871321]},"284":{"id":"284","outgoingArcs":["625"],"incomingArcs":["626"],"closestDespawnNode":null,"position":[3.8114473,46.9891335]},"164":{"id":"164","outgoingArcs":["605","606"],"incomingArcs":["604","609"],"position":[3.812754,46.9868076]},"285":{"id":"285","outgoingArcs":["626","627"],"incomingArcs":["625","634"],"position":[3.81125,46.9892042]},"165":{"id":"165","outgoingArcs":["603","604"],"incomingArcs":["601","606"],"position":[3.8127658,46.9867809]},"286":{"id":"286","outgoingArcs":["633","634"],"incomingArcs":["627","645"],"position":[3.8111239,46.9892833]},"166":{"id":"166","outgoingArcs":["601","602"],"incomingArcs":["603","677"],"position":[3.8127934,46.9867654]},"287":{"id":"287","outgoingArcs":["644","645"],"incomingArcs":["633","648"],"position":[3.8106419,46.989662]},"167":{"id":"167","outgoingArcs":["676","677"],"incomingArcs":["599","602"],"position":[3.8128329,46.9867535]},"288":{"id":"288","outgoingArcs":["459","460"],"incomingArcs":["445","469"],"position":[3.816589,46.98898]},"168":{"id":"168","outgoingArcs":["594","595","596"],"incomingArcs":["580","590","598"],"position":[3.8130339,46.9866357]},"289":{"id":"289","outgoingArcs":["469","470"],"incomingArcs":["460","479"],"position":[3.8166661,46.9890153]},"169":{"id":"169","outgoingArcs":["588","589","590"],"incomingArcs":["568","586","595"],"position":[3.8133296,46.9865453]},"60":{"id":"60","outgoingArcs":["253","254"],"incomingArcs":["251","255"],"position":[3.8090782,46.988341]},"61":{"id":"61","outgoingArcs":["255","256"],"incomingArcs":["254","258"],"position":[3.8091132,46.9884969]},"62":{"id":"62","outgoingArcs":["209","210"],"incomingArcs":["293","583"],"position":[3.8091177,46.9864739]},"63":{"id":"63","outgoingArcs":["581","582","583"],"incomingArcs":["210","292","578"],"position":[3.8092851,46.9864762]},"64":{"id":"64","outgoingArcs":["291","292"],"incomingArcs":["296","582"],"position":[3.8093482,46.986477]},"65":{"id":"65","outgoingArcs":["295","296"],"incomingArcs":["291","298"],"position":[3.8097245,46.986531]},"66":{"id":"66","outgoingArcs":["297","298"],"incomingArcs":["2","295"],"position":[3.8101028,46.9866243]},"67":{"id":"67","outgoingArcs":["249","250"],"incomingArcs":["144","246"],"position":[3.8087448,46.9879315]},"68":{"id":"68","outgoingArcs":["315","316","317"],"incomingArcs":["41","118","132"],"position":[3.8114461,46.9870572]},"69":{"id":"69","outgoingArcs":["443","444","445"],"incomingArcs":["431","436","459"],"position":[3.8161231,46.9887667]},"290":{"id":"290","outgoingArcs":["479","480"],"incomingArcs":["470","484"],"position":[3.8168224,46.9890651]},"170":{"id":"170","outgoingArcs":["586","587"],"incomingArcs":["585","588"],"position":[3.8134146,46.9865193]},"291":{"id":"291","outgoingArcs":["483","484"],"incomingArcs":["480","498"],"position":[3.8169399,46.9890874]},"171":{"id":"171","outgoingArcs":["584","585"],"incomingArcs":["565","587"],"position":[3.8134146,46.9864849]},"292":{"id":"292","outgoingArcs":["497","498"],"incomingArcs":["483","493"],"position":[3.8170888,46.9890956]},"172":{"id":"172","outgoingArcs":["565","566"],"incomingArcs":["562","584"],"position":[3.8132271,46.9862042]},"293":{"id":"293","outgoingArcs":["493","494"],"incomingArcs":["465","497"],"position":[3.8171925,46.9890949]},"173":{"id":"173","outgoingArcs":["561","562"],"incomingArcs":["563","566"],"position":[3.8131767,46.9861813]},"294":{"id":"294","outgoingArcs":["465","466"],"incomingArcs":["461","494"],"position":[3.8179259,46.9890094]},"174":{"id":"174","outgoingArcs":["563","564"],"incomingArcs":["561","567"],"position":[3.8131375,46.9861928]},"295":{"id":"295","outgoingArcs":["461","462"],"incomingArcs":["466","468"],"position":[3.8181152,46.9890035]},"175":{"id":"175","outgoingArcs":["567","568"],"incomingArcs":["564","589"],"position":[3.8131151,46.9862214]},"296":{"id":"296","outgoingArcs":["467","468"],"incomingArcs":["462","482"],"position":[3.8182911,46.9890114]},"176":{"id":"176","outgoingArcs":["30","31"],"incomingArcs":["35","107"],"position":[3.8134928,46.9913171]},"297":{"id":"297","outgoingArcs":["481","482"],"incomingArcs":["467","490"],"position":[3.8186616,46.9890689]},"177":{"id":"177","outgoingArcs":["107","108"],"incomingArcs":["31","284"],"position":[3.8135046,46.9908884]},"298":{"id":"298","outgoingArcs":["489","490"],"incomingArcs":["481","500"],"position":[3.8188152,46.9890894]},"178":{"id":"178","outgoingArcs":["284","285"],"incomingArcs":["79","108"],"position":[3.8134808,46.9906318]},"299":{"id":"299","outgoingArcs":["499","500"],"incomingArcs":["486","489"],"position":[3.8189888,46.9890959]},"179":{"id":"179","outgoingArcs":["78","79"],"incomingArcs":["91","285"],"position":[3.8133932,46.9903929]},"70":{"id":"70","outgoingArcs":["430","431"],"incomingArcs":["423","443"],"position":[3.8162706,46.9886544]},"71":{"id":"71","outgoingArcs":["423","424"],"incomingArcs":["413","430"],"position":[3.8163765,46.9885959]},"72":{"id":"72","outgoingArcs":["413","414"],"incomingArcs":["408","424"],"position":[3.8168038,46.9883976]},"73":{"id":"73","outgoingArcs":["407","408"],"incomingArcs":["399","414"],"position":[3.8169003,46.98835]},"74":{"id":"74","outgoingArcs":["399","400"],"incomingArcs":["372","407"],"position":[3.8169838,46.9882906]},"75":{"id":"75","outgoingArcs":["372","373"],"incomingArcs":["364","400"],"position":[3.8174274,46.9880093]},"76":{"id":"76","outgoingArcs":["364","365"],"incomingArcs":["359","373"],"position":[3.8176092,46.9879109]},"77":{"id":"77","outgoingArcs":["358","359"],"incomingArcs":["350","365"],"position":[3.8178212,46.9878091]},"78":{"id":"78","outgoingArcs":["350","351"],"incomingArcs":["347","358"],"position":[3.818073,46.9877037]},"79":{"id":"79","outgoingArcs":["346","347"],"incomingArcs":["343","351"],"position":[3.8182791,46.9876379]},"180":{"id":"180","outgoingArcs":["90","91"],"incomingArcs":["78","682"],"position":[3.813205,46.9900333]},"181":{"id":"181","outgoingArcs":["682","683"],"incomingArcs":["90","687"],"position":[3.8128264,46.9895141]},"182":{"id":"182","outgoingArcs":["448","449"],"incomingArcs":["151","433"],"position":[3.8073374,46.9887875]},"183":{"id":"183","outgoingArcs":["151","152"],"incomingArcs":["449","458"],"position":[3.8072164,46.9888938]},"184":{"id":"184","outgoingArcs":["457","458"],"incomingArcs":["152","472"],"position":[3.8071416,46.9889554]},"185":{"id":"185","outgoingArcs":["471","472"],"incomingArcs":["154","457"],"position":[3.8070407,46.9890168]},"186":{"id":"186","outgoingArcs":["153","154"],"incomingArcs":["471","506"],"position":[3.8068243,46.9891218]},"187":{"id":"187","outgoingArcs":["148","149"],"incomingArcs":["505","524"],"position":[3.80595,46.989363]},"188":{"id":"188","outgoingArcs":["150"],"incomingArcs":["525"],"closestDespawnNode":null,"position":[3.8038415,46.9898103]},"189":{"id":"189","outgoingArcs":["162","163"],"incomingArcs":["147","158"],"position":[3.8073539,46.9883173]},"80":{"id":"80","outgoingArcs":["342","343"],"incomingArcs":["338","346"],"position":[3.8185142,46.9875849]},"81":{"id":"81","outgoingArcs":["338","339"],"incomingArcs":["335","342"],"position":[3.8190227,46.9874864]},"82":{"id":"82","outgoingArcs":["334","335"],"incomingArcs":["332","339"],"position":[3.8195585,46.987403]},"83":{"id":"83","outgoingArcs":["332","333"],"incomingArcs":["330","334"],"position":[3.8196108,46.9873851]},"84":{"id":"84","outgoingArcs":["330","331"],"incomingArcs":["327","333"],"position":[3.819666,46.9873477]},"85":{"id":"85","outgoingArcs":["326","327"],"incomingArcs":["322","331"],"position":[3.8196893,46.9873115]},"86":{"id":"86","outgoingArcs":["322","323"],"incomingArcs":["320","326"],"position":[3.8197089,46.9872383]},"87":{"id":"87","outgoingArcs":["320","321"],"incomingArcs":["319","323"],"position":[3.8197048,46.9871729]},"88":{"id":"88","outgoingArcs":["318","319"],"incomingArcs":["313","321"],"position":[3.8196797,46.9870978]},"89":{"id":"89","outgoingArcs":["313","314"],"incomingArcs":["311","318"],"position":[3.8194406,46.9866797]},"190":{"id":"190","outgoingArcs":["158","159"],"incomingArcs":["163","403"],"position":[3.8064516,46.9883535]},"191":{"id":"191","outgoingArcs":["403","404"],"incomingArcs":["159","161"],"position":[3.806243,46.9883266]},"192":{"id":"192","outgoingArcs":["160","161"],"incomingArcs":["395","404"],"position":[3.8060656,46.9882772]},"193":{"id":"193","outgoingArcs":["269","270","271"],"incomingArcs":["272","630","643"],"position":[3.8098863,46.9893625]},"194":{"id":"194","outgoingArcs":["272","273"],"incomingArcs":["271","275"],"position":[3.8100015,46.9894366]},"195":{"id":"195","outgoingArcs":["274","275"],"incomingArcs":["273","277"],"position":[3.8101135,46.9895194]},"196":{"id":"196","outgoingArcs":["276","277"],"incomingArcs":["274","646"],"position":[3.8104088,46.989749]},"197":{"id":"197","outgoingArcs":["646","647","648"],"incomingArcs":["276","279","644"],"position":[3.8104277,46.9897841]},"198":{"id":"198","outgoingArcs":["278","279"],"incomingArcs":["280","647"],"position":[3.8105676,46.9900436]},"199":{"id":"199","outgoingArcs":["280","281"],"incomingArcs":["278","283"],"position":[3.8106216,46.9902559]},"90":{"id":"90","outgoingArcs":["311","312"],"incomingArcs":["307","314"],"position":[3.8194173,46.9866111]},"91":{"id":"91","outgoingArcs":["306","307"],"incomingArcs":["304","312"],"position":[3.819413,46.9865414]},"92":{"id":"92","outgoingArcs":["304","305"],"incomingArcs":["302","306"],"position":[3.8194117,46.9864552]},"93":{"id":"93","outgoingArcs":["302","303"],"incomingArcs":["301","305"],"position":[3.8193965,46.9864019]},"94":{"id":"94","outgoingArcs":["299","300","301"],"incomingArcs":["44","109","303"],"position":[3.819271,46.9861412]},"95":{"id":"95","outgoingArcs":["344","345"],"incomingArcs":["229","356"],"position":[3.8081437,46.9876237]},"96":{"id":"96","outgoingArcs":["356","357"],"incomingArcs":["344","378"],"position":[3.8082327,46.9878565]},"97":{"id":"97","outgoingArcs":["376","377","378"],"incomingArcs":["145","357","668"],"position":[3.8083414,46.9880253]},"98":{"id":"98","outgoingArcs":["504","505","506"],"incomingArcs":["148","153","421"],"position":[3.8064121,46.9892355]},"99":{"id":"99","outgoingArcs":["421","422"],"incomingArcs":["416","504"],"position":[3.8060194,46.9885253]},"300":{"id":"300","outgoingArcs":["485","486"],"incomingArcs":["488","499"],"position":[3.8195792,46.9890886]},"301":{"id":"301","outgoingArcs":["487","488"],"incomingArcs":["485","496"],"position":[3.8197708,46.9890888]},"302":{"id":"302","outgoingArcs":["495","496"],"incomingArcs":["487","501"],"position":[3.8199895,46.9890949]},"303":{"id":"303","outgoingArcs":["501"],"incomingArcs":["495"],"closestDespawnNode":null,"position":[3.8202039,46.9891134]},"304":{"id":"304","outgoingArcs":["70","71"],"incomingArcs":["32","84"],"position":[3.8109855,46.9876581]},"305":{"id":"305","outgoingArcs":["84","85"],"incomingArcs":["70","663"],"position":[3.8105901,46.9877031]},"306":{"id":"306","outgoingArcs":["662","663"],"incomingArcs":["25","85"],"position":[3.810509,46.9877234]},"307":{"id":"307","outgoingArcs":["24","25"],"incomingArcs":["72","662"],"position":[3.8104348,46.9877503]},"308":{"id":"308","outgoingArcs":["72","73"],"incomingArcs":["24","89"],"position":[3.8102645,46.9878456]},"309":{"id":"309","outgoingArcs":["88","89"],"incomingArcs":["23","73"],"position":[3.8100233,46.988024]},"310":{"id":"310","outgoingArcs":["22","23"],"incomingArcs":["74","88"],"position":[3.8099887,46.9880633]},"311":{"id":"311","outgoingArcs":["74","75"],"incomingArcs":["22","123"],"position":[3.8098903,46.9882695]},"312":{"id":"312","outgoingArcs":["242","243"],"incomingArcs":["131","679"],"position":[3.8123989,46.9871043]},"313":{"id":"313","outgoingArcs":["678","679"],"incomingArcs":["243","680"],"position":[3.812374,46.9871025]},"314":{"id":"314","outgoingArcs":["599","600"],"incomingArcs":["597","676"],"position":[3.8129556,46.9867178]},"315":{"id":"315","outgoingArcs":["597","598"],"incomingArcs":["596","600"],"position":[3.8130059,46.9866701]},"316":{"id":"316","outgoingArcs":["580"],"incomingArcs":["594"],"closestDespawnNode":null,"position":[3.8128912,46.986399]},"317":{"id":"317","outgoingArcs":["680","681"],"incomingArcs":["83","678"],"position":[3.8123027,46.9870973]},"318":{"id":"318","outgoingArcs":["124","125"],"incomingArcs":["48","697"],"position":[3.8121764,46.9877387]},"319":{"id":"319","outgoingArcs":["696","697"],"incomingArcs":["13","125"],"position":[3.8121898,46.9877425]},"320":{"id":"320","outgoingArcs":["686","687"],"incomingArcs":["683","685"],"position":[3.8127668,46.9894324]},"200":{"id":"200","outgoingArcs":["282","283"],"incomingArcs":["281","287"],"position":[3.8105771,46.990466]},"321":{"id":"321","outgoingArcs":["684","685"],"incomingArcs":["5","686"],"position":[3.812461,46.9889942]},"201":{"id":"201","outgoingArcs":["286","287"],"incomingArcs":["282","288"],"position":[3.8103859,46.9911365]},"322":{"id":"322","outgoingArcs":["5","6"],"incomingArcs":["63","684"],"position":[3.8124055,46.988859]},"202":{"id":"202","outgoingArcs":["288","289"],"incomingArcs":["286","290"],"position":[3.8101573,46.991483]},"323":{"id":"323","outgoingArcs":["62","63"],"incomingArcs":["6","425"],"position":[3.8123388,46.9886965]},"203":{"id":"203","outgoingArcs":["290"],"incomingArcs":["289"],"closestDespawnNode":null,"position":[3.8101192,46.9915914]},"324":{"id":"324","outgoingArcs":["425","426"],"incomingArcs":["1","62"],"position":[3.8123158,46.9886042]},"204":{"id":"204","outgoingArcs":["694","695"],"incomingArcs":["221","692"],"position":[3.8120897,46.9860271]},"325":{"id":"325","outgoingArcs":["0","1"],"incomingArcs":["410","426"],"position":[3.8123129,46.9885058]},"205":{"id":"205","outgoingArcs":["221","222"],"incomingArcs":["219","695"],"position":[3.8122793,46.9859137]},"326":{"id":"326","outgoingArcs":["409","410"],"incomingArcs":["0","12"],"position":[3.8123188,46.988385]},"206":{"id":"206","outgoingArcs":["219","220"],"incomingArcs":["217","222"],"position":[3.8128956,46.9854969]},"327":{"id":"327","outgoingArcs":["11","12"],"incomingArcs":["367","409"],"position":[3.8123566,46.9882065]},"207":{"id":"207","outgoingArcs":["217","218"],"incomingArcs":["220","667"],"position":[3.8133117,46.9852059]},"328":{"id":"328","outgoingArcs":["366","367"],"incomingArcs":["11","361"],"position":[3.8124741,46.987933]},"208":{"id":"208","outgoingArcs":["666","667"],"incomingArcs":["218","665"],"position":[3.8134114,46.9851205]},"329":{"id":"329","outgoingArcs":["360","361"],"incomingArcs":["16","366"],"position":[3.8124889,46.9878681]},"209":{"id":"209","outgoingArcs":["664","665"],"incomingArcs":["215","666"],"position":[3.8134758,46.9850409]},"330":{"id":"330","outgoingArcs":["382","383"],"incomingArcs":["14","688"],"position":[3.8132499,46.9880977]},"210":{"id":"210","outgoingArcs":["215","216"],"incomingArcs":["213","664"],"position":[3.8135179,46.9849615]},"331":{"id":"331","outgoingArcs":["45","46"],"incomingArcs":["130","690"],"position":[3.8125617,46.9871179]},"211":{"id":"211","outgoingArcs":["213","214"],"incomingArcs":["216","555"],"position":[3.8137278,46.9844118]},"332":{"id":"332","outgoingArcs":["692","693"],"incomingArcs":["224","694"],"position":[3.8120338,46.9860606]},"212":{"id":"212","outgoingArcs":["555"],"incomingArcs":["214"],"closestDespawnNode":null,"position":[3.8137615,46.9841964]},"213":{"id":"213","outgoingArcs":["391","392","393"],"incomingArcs":["385","434","689"],"position":[3.8137292,46.9882381]},"214":{"id":"214","outgoingArcs":["688","689"],"incomingArcs":["383","393"],"position":[3.8133086,46.9881178]},"215":{"id":"215","outgoingArcs":["109","110"],"incomingArcs":["51","299"],"position":[3.8186513,46.986349]},"216":{"id":"216","outgoingArcs":["51","52"],"incomingArcs":["110","138"],"position":[3.8181041,46.9865298]},"217":{"id":"217","outgoingArcs":["137","138"],"incomingArcs":["52","99"],"position":[3.8173898,46.9867564]},"218":{"id":"218","outgoingArcs":["99","100"],"incomingArcs":["59","137"],"position":[3.8168926,46.9869078]},"219":{"id":"219","outgoingArcs":["58","59"],"incomingArcs":["65","100"],"position":[3.8163072,46.9870843]},"220":{"id":"220","outgoingArcs":["64","65"],"incomingArcs":["58","97"],"position":[3.8161228,46.9871352]},"100":{"id":"100","outgoingArcs":["415","416"],"incomingArcs":["401","422"],"position":[3.805984,46.9884145]},"221":{"id":"221","outgoingArcs":["96","97","98"],"incomingArcs":["64","95","661"],"position":[3.8157052,46.9872012]},"101":{"id":"101","outgoingArcs":["401","402"],"incomingArcs":["396","415"],"position":[3.8059915,46.9883142]},"222":{"id":"222","outgoingArcs":["94","95"],"incomingArcs":["87","98"],"position":[3.815265,46.9872152]},"102":{"id":"102","outgoingArcs":["394","395","396"],"incomingArcs":["156","160","402"],"position":[3.8060117,46.9882531]},"223":{"id":"223","outgoingArcs":["86","87"],"incomingArcs":["94","114"],"position":[3.8144627,46.9871888]},"103":{"id":"103","outgoingArcs":["524","525","526"],"incomingArcs":["149","150","519"],"position":[3.8050717,46.9895493]},"224":{"id":"224","outgoingArcs":["114","115"],"incomingArcs":["7","86"],"position":[3.8138653,46.9871692]},"104":{"id":"104","outgoingArcs":["519","520"],"incomingArcs":["512","526"],"position":[3.805028,46.9894423]},"225":{"id":"225","outgoingArcs":["7","8"],"incomingArcs":["10","115"],"position":[3.8135208,46.9871553]},"105":{"id":"105","outgoingArcs":["511","512"],"incomingArcs":["508","520"],"position":[3.8049972,46.9893453]},"226":{"id":"226","outgoingArcs":["9","10"],"incomingArcs":["8","608"],"position":[3.8130153,46.9871391]},"106":{"id":"106","outgoingArcs":["507","508"],"incomingArcs":["429","511"],"position":[3.8049822,46.9892421]},"227":{"id":"227","outgoingArcs":["690","691"],"incomingArcs":["45","607"],"position":[3.8127051,46.9871261]},"107":{"id":"107","outgoingArcs":["427","428","429"],"incomingArcs":["412","442","507"],"position":[3.8050485,46.988627]},"228":{"id":"228","outgoingArcs":["143","144"],"incomingArcs":["249","669"],"position":[3.8085351,46.9879708]},"108":{"id":"108","outgoingArcs":["521","522","523"],"incomingArcs":["515","517","528"],"position":[3.8148367,46.9895084]},"229":{"id":"229","outgoingArcs":["668","669"],"incomingArcs":["143","377"],"position":[3.8083954,46.9880041]},"109":{"id":"109","outgoingArcs":["515","516"],"incomingArcs":["509","523"],"position":[3.8150577,46.9893988]}}